{"openapi":"3.0.0","paths":{"/api/v1/role":{"post":{"operationId":"RoleController_createRole","parameters":[],"requestBody":{"required":true,"content":{"application/json":{"schema":{"$ref":"#/components/schemas/CreateRoleDto"}}}},"responses":{"201":{"description":""}},"tags":["Role"]},"get":{"operationId":"RoleController_getRoles","parameters":[],"responses":{"200":{"description":""}},"tags":["Role"]}},"/api/v1/role/name/{nam}":{"get":{"operationId":"RoleController_getRoleByName","parameters":[{"name":"name","required":true,"in":"path","schema":{"type":"string"}}],"responses":{"200":{"description":""}},"tags":["Role"]}},"/api/v1/role/{id}":{"get":{"operationId":"RoleController_getRoleById","parameters":[{"name":"id","required":true,"in":"path","schema":{"type":"number"}}],"responses":{"200":{"description":""}},"tags":["Role"]},"put":{"operationId":"RoleController_updateRole","parameters":[{"name":"id","required":true,"in":"path","schema":{"type":"number"}}],"requestBody":{"required":true,"content":{"application/json":{"schema":{"$ref":"#/components/schemas/CreateRoleDto"}}}},"responses":{"200":{"description":""}},"tags":["Role"]}},"/api/v1/role/status/{id}":{"put":{"operationId":"RoleController_changeRoleStatus","parameters":[{"name":"id","required":true,"in":"path","schema":{"type":"number"}}],"requestBody":{"required":true,"content":{"application/json":{"schema":{"$ref":"#/components/schemas/RequestUpdateStatus"}}}},"responses":{"200":{"description":""}},"tags":["Role"]}},"/api/v1/role/privileges/{id}":{"get":{"operationId":"RoleController_getAssignedPrivilege","parameters":[{"name":"id","required":true,"in":"path","schema":{"type":"number"}}],"responses":{"200":{"description":""}},"tags":["Role"]}},"/api/v1/user/send":{"post":{"operationId":"UserController_sendEmail","parameters":[],"responses":{"201":{"description":""}},"tags":["User"]}},"/api/v1/user":{"post":{"operationId":"UserController_createUser","parameters":[],"requestBody":{"required":true,"content":{"application/json":{"schema":{"$ref":"#/components/schemas/RegisterUserDto"}}}},"responses":{"201":{"description":""}},"tags":["User"]},"get":{"operationId":"UserController_getUsers","parameters":[],"responses":{"200":{"description":""}},"tags":["User"]}},"/api/v1/user/{id}":{"get":{"operationId":"UserController_getUserById","parameters":[{"name":"id","required":true,"in":"path","schema":{"type":"number"}}],"responses":{"200":{"description":""}},"tags":["User"]}},"/api/v1/user/username/{username}":{"get":{"operationId":"UserController_getUserByUsername","parameters":[{"name":"username","required":true,"in":"path","schema":{"type":"string"}}],"responses":{"200":{"description":""}},"tags":["User"]}},"/api/v1/user/organization/{id}":{"get":{"operationId":"UserController_getOrganizationUsers","parameters":[{"name":"id","required":true,"in":"path","schema":{"type":"number"}}],"responses":{"200":{"description":""}},"tags":["User"]}},"/api/v1/privilege":{"post":{"operationId":"PrivilegeController_createPrivilege","parameters":[],"requestBody":{"required":true,"content":{"application/json":{"schema":{"$ref":"#/components/schemas/CreatePrivilegeDto"}}}},"responses":{"201":{"description":""}},"tags":["Privilege"]},"get":{"operationId":"PrivilegeController_getPrivileges","parameters":[],"responses":{"200":{"description":""}},"tags":["Privilege"]}},"/api/v1/privilege/{id}":{"put":{"operationId":"PrivilegeController_updatePrivilege","parameters":[{"name":"id","required":true,"in":"path","schema":{"type":"number"}}],"requestBody":{"required":true,"content":{"application/json":{"schema":{"$ref":"#/components/schemas/CreatePrivilegeDto"}}}},"responses":{"200":{"description":""}},"tags":["Privilege"]},"get":{"operationId":"PrivilegeController_getPrivilege","parameters":[{"name":"id","required":true,"in":"path","schema":{"type":"number"}}],"responses":{"200":{"description":""}},"tags":["Privilege"]}},"/api/v1/privilege/assign/{id}":{"put":{"operationId":"PrivilegeController_assignPrivilegeToRole","parameters":[{"name":"id","required":true,"in":"path","schema":{"type":"number"}}],"requestBody":{"required":true,"content":{"application/json":{"schema":{"type":"array","items":{"type":"string"}}}}},"responses":{"200":{"description":""}},"tags":["Privilege"]}},"/api/v1/auth/sign-up":{"post":{"operationId":"AuthController_signUp","parameters":[],"requestBody":{"required":true,"content":{"application/json":{"schema":{"$ref":"#/components/schemas/RegisterUserDto"}}}},"responses":{"201":{"description":""}},"tags":["Auth"]}},"/api/v1/auth/sign-in":{"post":{"operationId":"AuthController_signIn","parameters":[],"requestBody":{"required":true,"content":{"application/json":{"schema":{"$ref":"#/components/schemas/SigninDto"}}}},"responses":{"200":{"description":""}},"tags":["Auth"]}},"/api/v1/organization":{"post":{"operationId":"OrganizationController_createOrganization","parameters":[],"requestBody":{"required":true,"content":{"application/json":{"schema":{"$ref":"#/components/schemas/RegisterOrganizationDto"}}}},"responses":{"201":{"description":""}},"tags":["Organization"]},"get":{"operationId":"OrganizationController_getOrganizations","parameters":[],"responses":{"200":{"description":""}},"tags":["Organization"]}},"/api/v1/organization/{id}":{"put":{"operationId":"OrganizationController_updateOrganization","parameters":[{"name":"id","required":true,"in":"path","schema":{"type":"number"}}],"requestBody":{"required":true,"content":{"application/json":{"schema":{"$ref":"#/components/schemas/UpdateOrganizationDto"}}}},"responses":{"200":{"description":""}},"tags":["Organization"]},"get":{"operationId":"OrganizationController_getOneOrganization","parameters":[{"name":"id","required":true,"in":"path","schema":{"type":"number"}}],"responses":{"200":{"description":""}},"tags":["Organization"]}},"/api/v1/organization/status/{id}":{"put":{"operationId":"OrganizationController_changeOrganizationStatus","parameters":[{"name":"id","required":true,"in":"path","schema":{"type":"number"}}],"requestBody":{"required":true,"content":{"application/json":{"schema":{"$ref":"#/components/schemas/RequestUpdateStatus"}}}},"responses":{"200":{"description":""}},"tags":["Organization"]}},"/api/v1/license":{"post":{"operationId":"LicenseController_createLicense","parameters":[],"requestBody":{"required":true,"content":{"application/json":{"schema":{"$ref":"#/components/schemas/CreateLicenceDto"}}}},"responses":{"201":{"description":""}},"tags":["License"]},"get":{"operationId":"LicenseController_getLicenses","parameters":[],"responses":{"200":{"description":""}},"tags":["License"]}},"/api/v1/license/{id}":{"get":{"operationId":"LicenseController_getOneLicense","parameters":[{"name":"id","required":true,"in":"path","schema":{"type":"number"}}],"responses":{"200":{"description":""}},"tags":["License"]},"put":{"operationId":"LicenseController_updateLicense","parameters":[{"name":"id","required":true,"in":"path","schema":{"type":"number"}}],"requestBody":{"required":true,"content":{"application/json":{"schema":{"$ref":"#/components/schemas/CreateLicenceDto"}}}},"responses":{"200":{"description":""}},"tags":["License"]}},"/api/v1/licenseRequest":{"post":{"operationId":"LicenseRequestController_requestOrganizationLicense","parameters":[],"requestBody":{"required":true,"content":{"application/json":{"schema":{"$ref":"#/components/schemas/RequestLicenseDto"}}}},"responses":{"201":{"description":""}},"tags":["LicenseRequest"]},"get":{"operationId":"LicenseRequestController_getRequestedLicenses","parameters":[],"responses":{"200":{"description":""}},"tags":["LicenseRequest"]}},"/api/v1/licenseRequest/organization/{id}":{"get":{"operationId":"LicenseRequestController_getOrganizationRequestedLicense","parameters":[{"name":"id","required":true,"in":"path","schema":{"type":"number"}}],"responses":{"200":{"description":""}},"tags":["LicenseRequest"]}},"/api/v1/licenseRequest/{id}":{"get":{"operationId":"LicenseRequestController_getOneRequestedLicense","parameters":[{"name":"id","required":true,"in":"path","schema":{"type":"number"}}],"responses":{"200":{"description":""}},"tags":["LicenseRequest"]}},"/api/v1/licenseRequest/reportView/{id}":{"put":{"operationId":"LicenseRequestController_reportViewLicenseRequest","parameters":[{"name":"id","required":true,"in":"path","schema":{"type":"number"}}],"requestBody":{"required":true,"content":{"application/json":{"schema":{"$ref":"#/components/schemas/ReportViewLicenseDto"}}}},"responses":{"200":{"description":""}},"tags":["LicenseRequest"]}},"/api/v1/licenseRequest/decision/{id}":{"put":{"operationId":"LicenseRequestController_approveOrRejectLicenseRequest","parameters":[{"name":"id","required":true,"in":"path","schema":{"type":"number"}}],"requestBody":{"required":true,"content":{"application/json":{"schema":{"$ref":"#/components/schemas/DecisionLicenseRequestDto"}}}},"responses":{"200":{"description":""}},"tags":["LicenseRequest"]}},"/api/v1/licenseRequest/download/{id}":{"get":{"operationId":"LicenseRequestController_downloadOrganizationLicense","parameters":[{"name":"id","required":true,"in":"path","schema":{"type":"number"}}],"responses":{"200":{"description":""}},"tags":["LicenseRequest"]}},"/api/v1/licenseRequest/download/reference/{reference}":{"get":{"operationId":"LicenseRequestController_downloadOrganizationLicenseByReference","parameters":[{"name":"reference","required":true,"in":"path","schema":{"type":"string"}}],"responses":{"200":{"description":""}},"tags":["LicenseRequest"]}},"/api/v1/reports/organizationTypeStats":{"get":{"operationId":"ReportController_getOrganizationTypeStatus","parameters":[],"responses":{"200":{"description":""}},"tags":["Report"]}},"/api/v1/reports/licenseRequestStatusStats":{"get":{"operationId":"ReportController_getLicenseRequestStatusStats","parameters":[],"responses":{"200":{"description":""}},"tags":["Report"]}},"/api/v1/reports/generalStats":{"get":{"operationId":"ReportController_getGeneralStats","parameters":[],"responses":{"200":{"description":""}},"tags":["Report"]}},"/api/v1/reports/licenseRequestStatusStats/{orgId}":{"get":{"operationId":"ReportController_getLicenseRequestOrganizationStatusStats","parameters":[{"name":"orgId","required":true,"in":"path","schema":{"type":"number"}}],"responses":{"200":{"description":""}},"tags":["Report"]}},"/api/v1/reports/licenseTypeStats":{"get":{"operationId":"ReportController_getLicenseTypeStats","parameters":[],"responses":{"200":{"description":""}},"tags":["Report"]}},"/api/v1/reports/expires/{year}":{"get":{"operationId":"ReportController_getLicenseReportWithDayLeft","parameters":[{"name":"year","required":true,"in":"path","schema":{"type":"number"}}],"responses":{"200":{"description":""}},"tags":["Report"]}},"/api/v1/reports/recordedLicenseSummary":{"get":{"operationId":"ReportController_getRecordedLicenseSummary","parameters":[],"responses":{"200":{"description":""}},"tags":["Report"]}},"/api/v1/reports/totalContractDepartment/{id}":{"get":{"operationId":"ReportController_getTotalDepartment","parameters":[{"name":"id","required":true,"in":"path","schema":{"type":"number"}}],"responses":{"200":{"description":""}},"tags":["Report"]}},"/api/v1/reports/contractPeriodPayments/{id}":{"get":{"operationId":"ReportController_getContractPeriodPayments","parameters":[{"name":"id","required":true,"in":"path","schema":{"type":"number"}}],"responses":{"200":{"description":""}},"tags":["Report"]}},"/api/v1/reports/certificatesDepartment/{id}":{"get":{"operationId":"ReportController_getCertificateNumbers","parameters":[{"name":"id","required":true,"in":"path","schema":{"type":"number"}}],"responses":{"200":{"description":""}},"tags":["Report"]}},"/api/v1/reports/vendorPaymentsDepartment/{id}":{"get":{"operationId":"ReportController_getVendorPayments","parameters":[{"name":"id","required":true,"in":"path","schema":{"type":"number"}}],"responses":{"200":{"description":""}},"tags":["Report"]}},"/api/v1/reports/certificate":{"get":{"operationId":"ReportController_getCertificateReport","parameters":[],"responses":{"200":{"description":""}},"tags":["Report"]}},"/api/v1/reports/components":{"get":{"operationId":"ReportController_getComponentReport","parameters":[],"responses":{"200":{"description":""}},"tags":["Report"]}},"/api/v1/reports/systemTool":{"get":{"operationId":"ReportController_getSystemToolReport","parameters":[],"responses":{"200":{"description":""}},"tags":["Report"]}},"/api/v1/reports/metrics/certificate":{"get":{"operationId":"ReportController_getCertificateMetrics","parameters":[],"responses":{"200":{"description":""}},"tags":["Report"]}},"/api/v1/reports/metrics/all":{"get":{"operationId":"ReportController_getAllMetrics","parameters":[],"responses":{"200":{"description":""}},"tags":["Report"]}},"/api/v1/vendor":{"post":{"operationId":"VendorController_recordVendor","parameters":[],"requestBody":{"required":true,"content":{"application/json":{"schema":{"$ref":"#/components/schemas/RecordVendorDto"}}}},"responses":{"201":{"description":""}},"tags":["Vendor"]},"get":{"operationId":"VendorController_getVendors","parameters":[],"responses":{"200":{"description":""}},"tags":["Vendor"]}},"/api/v1/vendor/{id}":{"put":{"operationId":"VendorController_updateVendor","parameters":[{"name":"id","required":true,"in":"path","schema":{"type":"number"}}],"requestBody":{"required":true,"content":{"application/json":{"schema":{"$ref":"#/components/schemas/RecordVendorDto"}}}},"responses":{"200":{"description":""}},"tags":["Vendor"]}},"/api/v1/vendor/status/{id}":{"put":{"operationId":"VendorController_changeVendorStatus","parameters":[{"name":"id","required":true,"in":"path","schema":{"type":"number"}}],"requestBody":{"required":true,"content":{"application/json":{"schema":{"$ref":"#/components/schemas/ChangeVendorStatusDto"}}}},"responses":{"200":{"description":""}},"tags":["Vendor"]}},"/api/v1/vendor/upload":{"post":{"operationId":"VendorController_uploadVendor","parameters":[],"requestBody":{"required":true,"content":{"application/json":{"schema":{"type":"array","items":{"type":"string"}}}}},"responses":{"201":{"description":""}},"tags":["Vendor"]}},"/api/v1/ldapAuthentication":{"post":{"operationId":"LdapAuthenticationController_ldapAuthentication","parameters":[],"requestBody":{"required":true,"content":{"application/json":{"schema":{"$ref":"#/components/schemas/AuthenticationDto"}}}},"responses":{"200":{"description":""}},"tags":["LdapAuthentication"]}},"/api/v1/contract":{"post":{"operationId":"ContractController_createContract","parameters":[],"requestBody":{"required":true,"content":{"application/json":{"schema":{"$ref":"#/components/schemas/ContractDto"}}}},"responses":{"201":{"description":""}},"tags":["Contract"]},"get":{"operationId":"ContractController_getContracts","parameters":[],"responses":{"200":{"description":""}},"tags":["Contract"]}},"/api/v1/contract/{id}":{"put":{"operationId":"ContractController_updateContract","parameters":[{"name":"id","required":true,"in":"path","schema":{"type":"number"}}],"requestBody":{"required":true,"content":{"application/json":{"schema":{"$ref":"#/components/schemas/ContractDto"}}}},"responses":{"200":{"description":""}},"tags":["Contract"]},"get":{"operationId":"ContractController_getContractDetails","parameters":[{"name":"id","required":true,"in":"path","schema":{"type":"number"}}],"responses":{"200":{"description":""}},"tags":["Contract"]}},"/api/v1/contract/approvalStatus/{id}/{status}":{"put":{"operationId":"ContractController_updateApprovalStatus","parameters":[{"name":"id","required":true,"in":"path","schema":{"type":"number"}},{"name":"status","required":true,"in":"path","schema":{"type":"string"}}],"requestBody":{"required":true,"content":{"application/json":{"schema":{"$ref":"#/components/schemas/ApprovalDto"}}}},"responses":{"200":{"description":""}},"tags":["Contract"]}},"/api/v1/contract/component":{"post":{"operationId":"ContractController_createComponent","parameters":[],"requestBody":{"required":true,"content":{"application/json":{"schema":{"$ref":"#/components/schemas/ComponentDto"}}}},"responses":{"201":{"description":""}},"tags":["Contract"]}},"/api/v1/contract/component/{id}":{"get":{"operationId":"ContractController_getContractComponent","parameters":[{"name":"id","required":true,"in":"path","schema":{"type":"number"}}],"responses":{"200":{"description":""}},"tags":["Contract"]}},"/api/v1/contract/department/{id}":{"get":{"operationId":"ContractController_getContractDepartment","parameters":[{"name":"id","required":true,"in":"path","schema":{"type":"number"}}],"responses":{"200":{"description":""}},"tags":["Contract"]}},"/api/v1/contract/addSystemTool/{contractId}/{systemId}":{"put":{"operationId":"ContractController_addSystemToContract","parameters":[{"name":"contractId","required":true,"in":"path","schema":{"type":"number"}},{"name":"systemId","required":true,"in":"path","schema":{"type":"number"}}],"requestBody":{"required":true,"content":{"application/json":{"schema":{"$ref":"#/components/schemas/ContractToolDto"}}}},"responses":{"200":{"description":""}},"tags":["Contract"]}},"/api/v1/contract/removeSystemTool/{contractId}/{systemId}":{"put":{"operationId":"ContractController_removeSystemOnContract","parameters":[{"name":"contractId","required":true,"in":"path","schema":{"type":"number"}},{"name":"systemId","required":true,"in":"path","schema":{"type":"number"}}],"responses":{"200":{"description":""}},"tags":["Contract"]}},"/api/v1/contract/systemTool/{contractId}":{"get":{"operationId":"ContractController_getContractTools","parameters":[{"name":"contractId","required":true,"in":"path","schema":{"type":"number"}}],"responses":{"200":{"description":""}},"tags":["Contract"]}},"/api/v1/contract/reminder/{id}":{"put":{"operationId":"ContractController_removeReminder","parameters":[{"name":"id","required":true,"in":"path","schema":{"type":"number"}}],"responses":{"200":{"description":""}},"tags":["Contract"]}},"/api/v1/contract/metric/tool/{id}":{"get":{"operationId":"ContractController_getMetricTool","parameters":[{"name":"id","required":true,"in":"path","schema":{"type":"number"}}],"responses":{"200":{"description":""}},"tags":["Contract"]}},"/api/v1/contract/metric/component/{id}":{"get":{"operationId":"ContractController_getComponentTool","parameters":[{"name":"id","required":true,"in":"path","schema":{"type":"number"}}],"responses":{"200":{"description":""}},"tags":["Contract"]}},"/api/v1/contract/metric/tool/audit/{id}":{"put":{"operationId":"ContractController_addAuditMetricTool","parameters":[{"name":"id","required":true,"in":"path","schema":{"type":"number"}}],"requestBody":{"required":true,"content":{"application/json":{"schema":{"$ref":"#/components/schemas/AuditMetricDto"}}}},"responses":{"200":{"description":""}},"tags":["Contract"]}},"/api/v1/contract/metric/component/audit/{id}":{"put":{"operationId":"ContractController_addAuditMetricComponent","parameters":[{"name":"id","required":true,"in":"path","schema":{"type":"number"}}],"requestBody":{"required":true,"content":{"application/json":{"schema":{"$ref":"#/components/schemas/AuditMetricDto"}}}},"responses":{"200":{"description":""}},"tags":["Contract"]}},"/api/v1/contract/upload":{"post":{"operationId":"ContractController_uploadLicenseContract","parameters":[],"requestBody":{"required":true,"content":{"application/json":{"schema":{"type":"array","items":{"type":"string"}}}}},"responses":{"201":{"description":""}},"tags":["Contract"]}},"/api/v1/contract/tool/metric/department/{id}":{"get":{"operationId":"ContractController_getContractSystemToolMetrics","parameters":[{"name":"id","required":true,"in":"path","schema":{"type":"number"}}],"responses":{"200":{"description":""}},"tags":["Contract"]}},"/api/v1/contract/reminders/department/{id}":{"get":{"operationId":"ContractController_getContractsRemindersByDepartment","parameters":[{"name":"id","required":true,"in":"path","schema":{"type":"number"}}],"responses":{"200":{"description":""}},"tags":["Contract"]}},"/api/v1/systemTool":{"post":{"operationId":"SystemToolController_addNewSystemTool","parameters":[],"requestBody":{"required":true,"content":{"application/json":{"schema":{"$ref":"#/components/schemas/SystemToolDto"}}}},"responses":{"201":{"description":""}},"tags":["SystemTool"]},"get":{"operationId":"SystemToolController_getSystemTools","parameters":[],"responses":{"200":{"description":""}},"tags":["SystemTool"]}},"/api/v1/systemTool/{id}":{"put":{"operationId":"SystemToolController_updateSystemTool","parameters":[{"name":"id","required":true,"in":"path","schema":{"type":"number"}}],"requestBody":{"required":true,"content":{"application/json":{"schema":{"$ref":"#/components/schemas/SystemToolDto"}}}},"responses":{"200":{"description":""}},"tags":["SystemTool"]}},"/api/v1/systemTool/department/{departmentId}":{"get":{"operationId":"SystemToolController_getToolDepartment","parameters":[{"name":"departmentId","required":true,"in":"path","schema":{"type":"number"}}],"responses":{"200":{"description":""}},"tags":["SystemTool"]}},"/api/v1/systemTool/upload":{"post":{"operationId":"SystemToolController_uploadSystemTool","parameters":[],"requestBody":{"required":true,"content":{"application/json":{"schema":{"type":"array","items":{"type":"string"}}}}},"responses":{"201":{"description":""}},"tags":["SystemTool"]}},"/api/v1/metric":{"post":{"operationId":"MetricController_addMetric","parameters":[],"requestBody":{"required":true,"content":{"application/json":{"schema":{"$ref":"#/components/schemas/MetricDto"}}}},"responses":{"201":{"description":""}},"tags":["Metric"]},"get":{"operationId":"MetricController_getMetrics","parameters":[],"responses":{"200":{"description":""}},"tags":["Metric"]}},"/api/v1/metric/{id}":{"put":{"operationId":"MetricController_updateMetric","parameters":[{"name":"id","required":true,"in":"path","schema":{"type":"number"}}],"requestBody":{"required":true,"content":{"application/json":{"schema":{"$ref":"#/components/schemas/MetricDto"}}}},"responses":{"200":{"description":""}},"tags":["Metric"]}},"/api/v1/reportLicense":{"post":{"operationId":"ReportLicenseController_recordLicenseReport","parameters":[],"requestBody":{"required":true,"content":{"application/json":{"schema":{"$ref":"#/components/schemas/ReportLicenseDto"}}}},"responses":{"201":{"description":""}},"tags":["ReportLicense"]},"get":{"operationId":"ReportLicenseController_getRecordedLicenseReport","parameters":[],"responses":{"200":{"description":""}},"tags":["ReportLicense"]}},"/api/v1/reportLicense/department/{id}":{"get":{"operationId":"ReportLicenseController_getRecordedLicenseReportDepartment","parameters":[{"name":"id","required":true,"in":"path","schema":{"type":"number"}}],"responses":{"200":{"description":""}},"tags":["ReportLicense"]}},"/api/v1/reportLicense/{id}":{"put":{"operationId":"ReportLicenseController_updateReportedLicense","parameters":[{"name":"id","required":true,"in":"path","schema":{"type":"number"}}],"requestBody":{"required":true,"content":{"application/json":{"schema":{"$ref":"#/components/schemas/ReportLicenseDto"}}}},"responses":{"200":{"description":""}},"tags":["ReportLicense"]}},"/api/v1/systemFunction":{"post":{"operationId":"SystemFunctionsController_createSystemFunction","parameters":[],"requestBody":{"required":true,"content":{"application/json":{"schema":{"$ref":"#/components/schemas/SystemFunctionsDto"}}}},"responses":{"201":{"description":""}},"tags":["SystemFunctions"]},"get":{"operationId":"SystemFunctionsController_getSystemFunctions","parameters":[],"responses":{"200":{"description":""}},"tags":["SystemFunctions"]}},"/api/v1/systemFunction/{id}":{"put":{"operationId":"SystemFunctionsController_updateSystemFunction","parameters":[{"name":"id","required":true,"in":"path","schema":{"type":"number"}}],"requestBody":{"required":true,"content":{"application/json":{"schema":{"$ref":"#/components/schemas/SystemFunctionsDto"}}}},"responses":{"200":{"description":""}},"tags":["SystemFunctions"]}},"/api/v1/systemFunction/assign/{id}":{"put":{"operationId":"SystemFunctionsController_assignSystemTool","parameters":[{"name":"id","required":true,"in":"path","schema":{"type":"number"}}],"requestBody":{"required":true,"content":{"application/json":{"schema":{"type":"array","items":{"type":"string"}}}}},"responses":{"200":{"description":""}},"tags":["SystemFunctions"]}},"/api/v1/systemFunction/check/functions":{"put":{"operationId":"SystemFunctionsController_checkSimilarFunctionSystem","parameters":[],"requestBody":{"required":true,"content":{"application/json":{"schema":{"type":"array","items":{"type":"string"}}}}},"responses":{"200":{"description":""}},"tags":["SystemFunctions"]}},"/api/v1/department":{"post":{"operationId":"DepartmentsController_createDepartment","parameters":[],"requestBody":{"required":true,"content":{"application/json":{"schema":{"$ref":"#/components/schemas/DepartmentDto"}}}},"responses":{"201":{"description":""}},"tags":["Departments"]},"get":{"operationId":"DepartmentsController_getDepartments","parameters":[],"responses":{"200":{"description":""}},"tags":["Departments"]}},"/api/v1/department/{id}":{"put":{"operationId":"DepartmentsController_updateDepartment","parameters":[{"name":"id","required":true,"in":"path","schema":{"type":"number"}}],"responses":{"200":{"description":""}},"tags":["Departments"]}},"/api/v1/certificate":{"post":{"operationId":"CertificatesController_addCertificate","parameters":[],"requestBody":{"required":true,"content":{"application/json":{"schema":{"$ref":"#/components/schemas/CertificateDto"}}}},"responses":{"201":{"description":""}},"tags":["Certificates"]},"get":{"operationId":"CertificatesController_getCertificates","parameters":[],"responses":{"200":{"description":""}},"tags":["Certificates"]}},"/api/v1/certificate/department/{id}":{"get":{"operationId":"CertificatesController_getDepartmentCertificates","parameters":[{"name":"id","required":true,"in":"path","schema":{"type":"number"}}],"responses":{"200":{"description":""}},"tags":["Certificates"]}},"/api/v1/certificate/{id}":{"put":{"operationId":"CertificatesController_updateCertificate","parameters":[{"name":"id","required":true,"in":"path","schema":{"type":"number"}}],"requestBody":{"required":true,"content":{"application/json":{"schema":{"$ref":"#/components/schemas/CertificateDto"}}}},"responses":{"200":{"description":""}},"tags":["Certificates"]}},"/api/v1/certificate/report":{"post":{"operationId":"CertificatesController_reportCertificate","parameters":[],"requestBody":{"required":true,"content":{"application/json":{"schema":{"$ref":"#/components/schemas/CertificateReportDto"}}}},"responses":{"201":{"description":""}},"tags":["Certificates"]},"get":{"operationId":"CertificatesController_getReportedCertificates","parameters":[],"responses":{"200":{"description":""}},"tags":["Certificates"]}},"/api/v1/certificate/report/certificate/{id}":{"get":{"operationId":"CertificatesController_getReportedCertificateByCertificate","parameters":[{"name":"id","required":true,"in":"path","schema":{"type":"number"}}],"responses":{"200":{"description":""}},"tags":["Certificates"]}},"/api/v1/certificate/report/user/{id}":{"get":{"operationId":"CertificatesController_getReportedCertificateByUser","parameters":[{"name":"id","required":true,"in":"path","schema":{"type":"number"}}],"responses":{"200":{"description":""}},"tags":["Certificates"]}},"/api/v1/certificate/upload":{"post":{"operationId":"CertificatesController_uploadCertificate","parameters":[],"requestBody":{"required":true,"content":{"application/json":{"schema":{"type":"array","items":{"type":"string"}}}}},"responses":{"201":{"description":""}},"tags":["Certificates"]}},"/api/v1/certificate/reminders/department/{id}":{"get":{"operationId":"CertificatesController_getReminders","parameters":[{"name":"id","required":true,"in":"path","schema":{"type":"number"}}],"responses":{"200":{"description":""}},"tags":["Certificates"]}}},"info":{"title":"API","description":"Auto Swagger Docs","version":"1.0","contact":{}},"tags":[],"servers":[],"components":{"securitySchemes":{"bearer":{"scheme":"bearer","bearerFormat":"JWT","type":"http"}},"schemas":{"CreateRoleDto":{"type":"object","properties":{}},"RequestUpdateStatus":{"type":"object","properties":{}},"RegisterUserDto":{"type":"object","properties":{}},"CreatePrivilegeDto":{"type":"object","properties":{}},"SigninDto":{"type":"object","properties":{}},"RegisterOrganizationDto":{"type":"object","properties":{}},"UpdateOrganizationDto":{"type":"object","properties":{}},"CreateLicenceDto":{"type":"object","properties":{}},"RequestLicenseDto":{"type":"object","properties":{}},"ReportViewLicenseDto":{"type":"object","properties":{}},"DecisionLicenseRequestDto":{"type":"object","properties":{}},"RecordVendorDto":{"type":"object","properties":{}},"ChangeVendorStatusDto":{"type":"object","properties":{}},"AuthenticationDto":{"type":"object","properties":{}},"ContractDto":{"type":"object","properties":{}},"ApprovalDto":{"type":"object","properties":{}},"ComponentDto":{"type":"object","properties":{}},"ContractToolDto":{"type":"object","properties":{}},"ReminderDto":{"type":"object","properties":{}},"AuditMetricDto":{"type":"object","properties":{}},"SystemToolDto":{"type":"object","properties":{}},"MetricDto":{"type":"object","properties":{}},"ReportLicenseDto":{"type":"object","properties":{}},"SystemFunctionsDto":{"type":"object","properties":{}},"DepartmentDto":{"type":"object","properties":{}},"CertificateDto":{"type":"object","properties":{}},"CertificateReportDto":{"type":"object","properties":{}}}}}